aiopsconnector/__init__.py
aiopsconnector/base.py
aiopsconnector/mg_cntr.py
aiopsconnector/pg_cntr.py
aiopsconnector-1.0.4.dist-info/LICENSE
aiopsconnector-1.0.4.dist-info/METADATA
aiopsconnector-1.0.4.dist-info/WHEEL
aiopsconnector-1.0.4.dist-info/top_level.txt
aiopsconnector-1.0.4.dist-info/RECORD
